django_thumbmark/__init__.py
django_thumbmark/apps.py
django_thumbmark/decorators.py
django_thumbmark/urls.py
django_thumbmark/views.py
django_thumbmark/templates/django_thumbmark/base.html
django_thumbmark/templates/django_thumbmark/login.html
django_thumbmark-0.2.dist-info/LICENSE
django_thumbmark-0.2.dist-info/METADATA
django_thumbmark-0.2.dist-info/WHEEL
django_thumbmark-0.2.dist-info/top_level.txt
django_thumbmark-0.2.dist-info/RECORD
